hands_to_text/__init__.py
hands_to_text/text/__init__.py
hands_to_text/text/abstract.py
hands_to_text/text/processor.py
hands_to_text/text/strategy.py
hands_to_text/video/__init__.py
hands_to_text/video/images.py
hands_to_text/video/models.py
hands_to_text-0.1.0.dist-info/METADATA
hands_to_text-0.1.0.dist-info/WHEEL
hands_to_text-0.1.0.dist-info/RECORD
